{"updated": "2026-07-01T18:18:23+09:00", "items": {"metal:M04020000": {"name": "금(국내)", "price": 197190.0, "pct": -0.63, "type": "metal"}, "exchange:FX_USDKRW": {"name": "원/달러", "price": 1555.3, "pct": 0.47, "type": "exchange"}, "kr:005930": {"name": "삼성전자", "price": 314500.0, "pct": -5.84, "type": "kr"}, "us:NVDA.O": {"name": "엔비디아", "price": 200.09, "pct": 2.63, "type": "us"}, "kr:0173Y0": {"name": "KODEX 미국AI광통신네트워크", "price": 15175.0, "pct": 0.43, "type": "kr"}, "kr:000660": {"name": "SK하이닉스", "price": 2560000.0, "pct": -3.4, "type": "kr"}, "us:TSLA.O": {"name": "Tesla, Inc.", "price": 420.6, "pct": 2.13, "type": "us"}, "us:GOOG.O": {"name": "Alphabet Inc.", "price": 353.33, "pct": 0.58, "type": "us"}}}