{"updated": "2026-07-10T09:55:27+09:00", "items": {"metal:M04020000": {"name": "금(국내)", "price": 199450.0, "pct": 0.83, "type": "metal"}, "exchange:FX_USDKRW": {"name": "원/달러", "price": 1508.9, "pct": 0.13, "type": "exchange"}, "kr:005930": {"name": "삼성전자", "price": 287750.0, "pct": 3.51, "type": "kr"}, "us:NVDA.O": {"name": "엔비디아", "price": 202.78, "pct": -0.66, "type": "us"}, "kr:0173Y0": {"name": "KODEX 미국AI광통신네트워크", "price": 13030.0, "pct": 4.12, "type": "kr"}, "kr:000660": {"name": "SK하이닉스", "price": 2201000.0, "pct": 0.69, "type": "kr"}, "us:TSLA.O": {"name": "Tesla, Inc.", "price": 406.55, "pct": 3.17, "type": "us"}, "us:GOOG.O": {"name": "Alphabet Inc.", "price": 356.24, "pct": -0.69, "type": "us"}}}